[
  {
    "inter": {
      "time": "2017-01-06T02:20:05.362660878795Z",
      "lat": -33.3589166,
      "fixFrac": 13.272532175759245,
      "lng": 147.93645594,
      "alt": 307.27
    },
    "cross": {
      "inZone": [
        true,
        false
      ],
      "crossingPair": [
        {
          "time": "2017-01-06T02:20:04Z",
          "lat": -33.35881667,
          "fix": 13,
          "lng": 147.93628333,
          "alt": 307
        },
        {
          "time": "2017-01-06T02:20:09Z",
          "lat": -33.35918333,
          "fix": 14,
          "lng": 147.93691667,
          "alt": 308
        }
      ]
    }
  },
  {
    "inter": {
      "time": "2017-01-06T02:46:30.379055785265Z",
      "lat": -33.33389639,
      "fixFrac": 331.6758111570533,
      "lng": 147.82875293,
      "alt": 2299.81
    },
    "cross": {
      "inZone": [
        true,
        false
      ],
      "crossingPair": [
        {
          "time": "2017-01-06T02:46:27Z",
          "lat": -33.33416667,
          "fix": 331,
          "lng": 147.82976667,
          "alt": 2314
        },
        {
          "time": "2017-01-06T02:46:32Z",
          "lat": -33.33376667,
          "fix": 332,
          "lng": 147.82826667,
          "alt": 2293
        }
      ]
    }
  },
  {
    "inter": {
      "time": "2017-01-06T05:48:35.073532352796Z",
      "lat": -33.60818634,
      "fixFrac": 2511.5183830881992,
      "lng": 146.00334945,
      "alt": 2377.96
    },
    "cross": {
      "inZone": [
        false,
        true
      ],
      "crossingPair": [
        {
          "time": "2017-01-06T05:48:33Z",
          "lat": -33.60786667,
          "fix": 2511,
          "lng": 146.0036,
          "alt": 2379
        },
        {
          "time": "2017-01-06T05:48:37Z",
          "lat": -33.60848333,
          "fix": 2512,
          "lng": 146.00311667,
          "alt": 2377
        }
      ]
    }
  },
  {
    "inter": {
      "time": "2017-01-06T06:28:22.62650485657Z",
      "lat": -33.49329433,
      "fixFrac": 2988.925300971314,
      "lng": 145.52867076,
      "alt": 307.64
    },
    "cross": {
      "inZone": [
        false,
        true
      ],
      "crossingPair": [
        {
          "time": "2017-01-06T06:28:18Z",
          "lat": -33.49405,
          "fix": 2988,
          "lng": 145.53016667,
          "alt": 328
        },
        {
          "time": "2017-01-06T06:28:23Z",
          "lat": -33.49323333,
          "fix": 2989,
          "lng": 145.52855,
          "alt": 306
        }
      ]
    }
  }
]
