[
  {
    "inter": {
      "time": "2017-01-05T02:15:44.41513361179Z",
      "lat": -33.35903321,
      "fixFrac": 33.083026722358504,
      "lng": 147.93628863,
      "alt": 288
    },
    "cross": {
      "inZone": [
        true,
        false
      ],
      "crossingPair": [
        {
          "time": "2017-01-05T02:15:44Z",
          "lat": -33.359,
          "fix": 33,
          "lng": 147.93621667,
          "alt": 287
        },
        {
          "time": "2017-01-05T02:15:49Z",
          "lat": -33.3594,
          "fix": 34,
          "lng": 147.93708333,
          "alt": 299
        }
      ]
    }
  },
  {
    "inter": {
      "time": "2017-01-05T02:45:24.486550266055Z",
      "lat": -33.28271082,
      "fixFrac": 389.0973100532118,
      "lng": 147.87063625,
      "alt": 2202.68
    },
    "cross": {
      "inZone": [
        true,
        false
      ],
      "crossingPair": [
        {
          "time": "2017-01-05T02:45:24Z",
          "lat": -33.2828,
          "fix": 389,
          "lng": 147.87068333,
          "alt": 2202
        },
        {
          "time": "2017-01-05T02:45:29Z",
          "lat": -33.28188333,
          "fix": 390,
          "lng": 147.8702,
          "alt": 2209
        }
      ]
    }
  },
  {
    "inter": {
      "time": "2017-01-05T04:09:06.35740494835Z",
      "lat": -32.82888424,
      "fixFrac": 1390.6714809896703,
      "lng": 147.49471094,
      "alt": 1008.24
    },
    "cross": {
      "inZone": [
        false,
        true
      ],
      "crossingPair": [
        {
          "time": "2017-01-05T04:09:03Z",
          "lat": -32.82953333,
          "fix": 1390,
          "lng": 147.49473333,
          "alt": 1021
        },
        {
          "time": "2017-01-05T04:09:08Z",
          "lat": -32.82856667,
          "fix": 1391,
          "lng": 147.4947,
          "alt": 1002
        }
      ]
    }
  },
  {
    "inter": {
      "time": "2017-01-05T05:20:19.317595097875Z",
      "lat": -32.90468565,
      "fixFrac": 2244.863519019575,
      "lng": 147.98175976,
      "alt": 1177.41
    },
    "cross": {
      "inZone": [
        false,
        true
      ],
      "crossingPair": [
        {
          "time": "2017-01-05T05:20:15Z",
          "lat": -32.90501667,
          "fix": 2244,
          "lng": 147.98108333,
          "alt": 1180
        },
        {
          "time": "2017-01-05T05:20:20Z",
          "lat": -32.90463333,
          "fix": 2245,
          "lng": 147.98186667,
          "alt": 1177
        }
      ]
    }
  },
  null
]
