{
  "zonesCrossNominees": [
    [
      {
        "inZone": [
          true,
          false
        ],
        "crossingPair": [
          {
            "time": "2017-01-05T02:13:51Z",
            "lat": -33.35838333,
            "fix": 77,
            "lng": 147.937,
            "alt": 252
          },
          {
            "time": "2017-01-05T02:13:52Z",
            "lat": -33.35848333,
            "fix": 78,
            "lng": 147.9372,
            "alt": 255
          }
        ]
      },
      {
        "inZone": [
          false,
          true
        ],
        "crossingPair": [
          {
            "time": "2017-01-05T02:20:33Z",
            "lat": -33.35523333,
            "fix": 449,
            "lng": 147.93781667,
            "alt": 1260
          },
          {
            "time": "2017-01-05T02:20:34Z",
            "lat": -33.35525,
            "fix": 450,
            "lng": 147.93766667,
            "alt": 1265
          }
        ]
      },
      {
        "inZone": [
          true,
          false
        ],
        "crossingPair": [
          {
            "time": "2017-01-05T02:20:43Z",
            "lat": -33.35433333,
            "fix": 459,
            "lng": 147.93726667,
            "alt": 1301
          },
          {
            "time": "2017-01-05T02:20:44Z",
            "lat": -33.35426667,
            "fix": 460,
            "lng": 147.93733333,
            "alt": 1306
          }
        ]
      },
      {
        "inZone": [
          false,
          true
        ],
        "crossingPair": [
          {
            "time": "2017-01-05T02:20:53Z",
            "lat": -33.35445,
            "fix": 469,
            "lng": 147.93781667,
            "alt": 1329
          },
          {
            "time": "2017-01-05T02:20:55Z",
            "lat": -33.35501667,
            "fix": 470,
            "lng": 147.93745,
            "alt": 1334
          }
        ]
      },
      {
        "inZone": [
          true,
          false
        ],
        "crossingPair": [
          {
            "time": "2017-01-05T02:22:21Z",
            "lat": -33.35375,
            "fix": 552,
            "lng": 147.93666667,
            "alt": 1548
          },
          {
            "time": "2017-01-05T02:22:22Z",
            "lat": -33.35363333,
            "fix": 553,
            "lng": 147.93696667,
            "alt": 1552
          }
        ]
      },
      {
        "inZone": [
          false,
          true
        ],
        "crossingPair": [
          {
            "time": "2017-01-05T02:22:39Z",
            "lat": -33.35426667,
            "fix": 569,
            "lng": 147.93728333,
            "alt": 1570
          },
          {
            "time": "2017-01-05T02:22:40Z",
            "lat": -33.35431667,
            "fix": 570,
            "lng": 147.9372,
            "alt": 1573
          }
        ]
      },
      {
        "inZone": [
          true,
          false
        ],
        "crossingPair": [
          {
            "time": "2017-01-05T02:22:48Z",
            "lat": -33.35383333,
            "fix": 578,
            "lng": 147.93666667,
            "alt": 1583
          },
          {
            "time": "2017-01-05T02:22:49Z",
            "lat": -33.35365,
            "fix": 579,
            "lng": 147.93668333,
            "alt": 1584
          }
        ]
      },
      {
        "inZone": [
          false,
          true
        ],
        "crossingPair": [
          {
            "time": "2017-01-05T02:23:27Z",
            "lat": -33.35475,
            "fix": 613,
            "lng": 147.93768333,
            "alt": 1598
          },
          {
            "time": "2017-01-05T02:23:29Z",
            "lat": -33.3549,
            "fix": 614,
            "lng": 147.93745,
            "alt": 1598
          }
        ]
      },
      {
        "inZone": [
          true,
          false
        ],
        "crossingPair": [
          {
            "time": "2017-01-05T02:24:48Z",
            "lat": -33.35965,
            "fix": 687,
            "lng": 147.93455,
            "alt": 1718
          },
          {
            "time": "2017-01-05T02:24:49Z",
            "lat": -33.35973333,
            "fix": 688,
            "lng": 147.93468333,
            "alt": 1718
          }
        ]
      },
      {
        "inZone": [
          false,
          true
        ],
        "crossingPair": [
          {
            "time": "2017-01-05T02:25:17Z",
            "lat": -33.3597,
            "fix": 714,
            "lng": 147.93216667,
            "alt": 1733
          },
          {
            "time": "2017-01-05T02:25:18Z",
            "lat": -33.35948333,
            "fix": 715,
            "lng": 147.93203333,
            "alt": 1738
          }
        ]
      },
      {
        "inZone": [
          true,
          false
        ],
        "crossingPair": [
          {
            "time": "2017-01-05T02:25:51Z",
            "lat": -33.35535,
            "fix": 743,
            "lng": 147.92961667,
            "alt": 1766
          },
          {
            "time": "2017-01-05T02:25:52Z",
            "lat": -33.35508333,
            "fix": 744,
            "lng": 147.92941667,
            "alt": 1764
          }
        ]
      }
    ],
    [
      {
        "inZone": [
          true,
          false
        ],
        "crossingPair": [
          {
            "time": "2017-01-05T02:45:03Z",
            "lat": -33.28278333,
            "fix": 1777,
            "lng": 147.87085,
            "alt": 2045
          },
          {
            "time": "2017-01-05T02:45:04Z",
            "lat": -33.28258333,
            "fix": 1778,
            "lng": 147.87071667,
            "alt": 2046
          }
        ]
      },
      {
        "inZone": [
          false,
          true
        ],
        "crossingPair": [
          {
            "time": "2017-01-05T02:45:14Z",
            "lat": -33.28195,
            "fix": 1787,
            "lng": 147.8718,
            "alt": 2054
          },
          {
            "time": "2017-01-05T02:45:15Z",
            "lat": -33.28201667,
            "fix": 1788,
            "lng": 147.87186667,
            "alt": 2056
          }
        ]
      },
      {
        "inZone": [
          true,
          false
        ],
        "crossingPair": [
          {
            "time": "2017-01-05T02:45:27Z",
            "lat": -33.283,
            "fix": 1799,
            "lng": 147.87035,
            "alt": 2074
          },
          {
            "time": "2017-01-05T02:45:28Z",
            "lat": -33.28298333,
            "fix": 1800,
            "lng": 147.87016667,
            "alt": 2076
          }
        ]
      }
    ],
    [
      {
        "inZone": [
          false,
          true
        ],
        "crossingPair": [
          {
            "time": "2017-01-05T04:15:43Z",
            "lat": -32.81326667,
            "fix": 6860,
            "lng": 147.50221667,
            "alt": 1760
          },
          {
            "time": "2017-01-05T04:15:44Z",
            "lat": -32.81325,
            "fix": 6861,
            "lng": 147.502,
            "alt": 1761
          }
        ]
      },
      {
        "inZone": [
          true,
          false
        ],
        "crossingPair": [
          {
            "time": "2017-01-05T04:17:28Z",
            "lat": -32.81766667,
            "fix": 6956,
            "lng": 147.50073333,
            "alt": 1879
          },
          {
            "time": "2017-01-05T04:17:29Z",
            "lat": -32.81771667,
            "fix": 6957,
            "lng": 147.5009,
            "alt": 1880
          }
        ]
      }
    ],
    [
      {
        "inZone": [
          false,
          true
        ],
        "crossingPair": [
          {
            "time": "2017-01-05T05:29:03Z",
            "lat": -32.90578333,
            "fix": 10897,
            "lng": 147.9837,
            "alt": 2151
          },
          {
            "time": "2017-01-05T05:29:04Z",
            "lat": -32.9057,
            "fix": 10898,
            "lng": 147.98383333,
            "alt": 2149
          }
        ]
      },
      {
        "inZone": [
          true,
          false
        ],
        "crossingPair": [
          {
            "time": "2017-01-05T05:29:14Z",
            "lat": -32.90568333,
            "fix": 10908,
            "lng": 147.98548333,
            "alt": 2125
          },
          {
            "time": "2017-01-05T05:29:15Z",
            "lat": -32.90581667,
            "fix": 10909,
            "lng": 147.98561667,
            "alt": 2124
          }
        ]
      }
    ],
    [
      {
        "inZone": [
          false,
          true
        ],
        "crossingPair": [
          {
            "time": "2017-01-05T05:53:42Z",
            "lat": -33.12216667,
            "fix": 12219,
            "lng": 147.9111,
            "alt": 365
          },
          {
            "time": "2017-01-05T05:53:43Z",
            "lat": -33.12238333,
            "fix": 12220,
            "lng": 147.9111,
            "alt": 363
          }
        ]
      },
      {
        "inZone": [
          true,
          false
        ],
        "crossingPair": [
          {
            "time": "2017-01-05T05:54:01Z",
            "lat": -33.12278333,
            "fix": 12236,
            "lng": 147.90856667,
            "alt": 324
          },
          {
            "time": "2017-01-05T05:54:02Z",
            "lat": -33.12273333,
            "fix": 12237,
            "lng": 147.90836667,
            "alt": 323
          }
        ]
      },
      {
        "inZone": [
          false,
          true
        ],
        "crossingPair": [
          {
            "time": "2017-01-05T05:54:27Z",
            "lat": -33.12435,
            "fix": 12262,
            "lng": 147.90641667,
            "alt": 277
          },
          {
            "time": "2017-01-05T05:54:28Z",
            "lat": -33.12438333,
            "fix": 12263,
            "lng": 147.90655,
            "alt": 277
          }
        ]
      }
    ]
  ],
  "zonesCrossExcluded": [],
  "startSelected": [
    "2017-01-05T02:45:00Z",
    {
      "inZone": [
        true,
        false
      ],
      "crossingPair": [
        {
          "time": "2017-01-05T02:45:27Z",
          "lat": -33.283,
          "fix": 1799,
          "lng": 147.87035,
          "alt": 2074
        },
        {
          "time": "2017-01-05T02:45:28Z",
          "lat": -33.28298333,
          "fix": 1800,
          "lng": 147.87016667,
          "alt": 2076
        }
      ]
    }
  ],
  "zonesCrossSelected": [
    {
      "inZone": [
        true,
        false
      ],
      "crossingPair": [
        {
          "time": "2017-01-05T02:13:51Z",
          "lat": -33.35838333,
          "fix": 77,
          "lng": 147.937,
          "alt": 252
        },
        {
          "time": "2017-01-05T02:13:52Z",
          "lat": -33.35848333,
          "fix": 78,
          "lng": 147.9372,
          "alt": 255
        }
      ]
    },
    {
      "inZone": [
        true,
        false
      ],
      "crossingPair": [
        {
          "time": "2017-01-05T02:45:27Z",
          "lat": -33.283,
          "fix": 1799,
          "lng": 147.87035,
          "alt": 2074
        },
        {
          "time": "2017-01-05T02:45:28Z",
          "lat": -33.28298333,
          "fix": 1800,
          "lng": 147.87016667,
          "alt": 2076
        }
      ]
    },
    {
      "inZone": [
        false,
        true
      ],
      "crossingPair": [
        {
          "time": "2017-01-05T04:15:43Z",
          "lat": -32.81326667,
          "fix": 6860,
          "lng": 147.50221667,
          "alt": 1760
        },
        {
          "time": "2017-01-05T04:15:44Z",
          "lat": -32.81325,
          "fix": 6861,
          "lng": 147.502,
          "alt": 1761
        }
      ]
    },
    {
      "inZone": [
        false,
        true
      ],
      "crossingPair": [
        {
          "time": "2017-01-05T05:29:03Z",
          "lat": -32.90578333,
          "fix": 10897,
          "lng": 147.9837,
          "alt": 2151
        },
        {
          "time": "2017-01-05T05:29:04Z",
          "lat": -32.9057,
          "fix": 10898,
          "lng": 147.98383333,
          "alt": 2149
        }
      ]
    },
    {
      "inZone": [
        false,
        true
      ],
      "crossingPair": [
        {
          "time": "2017-01-05T05:53:42Z",
          "lat": -33.12216667,
          "fix": 12219,
          "lng": 147.9111,
          "alt": 365
        },
        {
          "time": "2017-01-05T05:53:43Z",
          "lat": -33.12238333,
          "fix": 12220,
          "lng": 147.9111,
          "alt": 363
        }
      ]
    }
  ],
  "startNominees": [
    [
      "2017-01-05T03:45:00Z",
      []
    ],
    [
      "2017-01-05T03:30:00Z",
      []
    ],
    [
      "2017-01-05T03:15:00Z",
      []
    ],
    [
      "2017-01-05T03:00:00Z",
      []
    ],
    [
      "2017-01-05T02:45:00Z",
      [
        {
          "inZone": [
            true,
            false
          ],
          "crossingPair": [
            {
              "time": "2017-01-05T02:45:03Z",
              "lat": -33.28278333,
              "fix": 1777,
              "lng": 147.87085,
              "alt": 2045
            },
            {
              "time": "2017-01-05T02:45:04Z",
              "lat": -33.28258333,
              "fix": 1778,
              "lng": 147.87071667,
              "alt": 2046
            }
          ]
        },
        {
          "inZone": [
            true,
            false
          ],
          "crossingPair": [
            {
              "time": "2017-01-05T02:45:27Z",
              "lat": -33.283,
              "fix": 1799,
              "lng": 147.87035,
              "alt": 2074
            },
            {
              "time": "2017-01-05T02:45:28Z",
              "lat": -33.28298333,
              "fix": 1800,
              "lng": 147.87016667,
              "alt": 2076
            }
          ]
        }
      ]
    ],
    [
      "2017-01-05T02:30:00Z",
      []
    ]
  ]
}
