[
  {
    "inter": {
      "time": "2016-12-31T04:04:21.902334364442Z",
      "lat": -33.35744675,
      "fixFrac": 23.451167182221127,
      "lng": 147.92953721,
      "alt": 396.8
    },
    "cross": {
      "inZone": [
        true,
        false
      ],
      "crossingPair": [
        {
          "time": "2016-12-31T04:04:21Z",
          "lat": -33.35741667,
          "fix": 23,
          "lng": 147.92965,
          "alt": 395
        },
        {
          "time": "2016-12-31T04:04:23Z",
          "lat": -33.35748333,
          "fix": 24,
          "lng": 147.9294,
          "alt": 399
        }
      ]
    }
  },
  {
    "inter": {
      "time": "2016-12-31T04:46:25.660713617352Z",
      "lat": -33.29760089,
      "fixFrac": 1283.330356808677,
      "lng": 148.01595475,
      "alt": 1871.02
    },
    "cross": {
      "inZone": [
        true,
        false
      ],
      "crossingPair": [
        {
          "time": "2016-12-31T04:46:25Z",
          "lat": -33.2977,
          "fix": 1283,
          "lng": 148.01586667,
          "alt": 1873
        },
        {
          "time": "2016-12-31T04:46:27Z",
          "lat": -33.2974,
          "fix": 1284,
          "lng": 148.01613333,
          "alt": 1867
        }
      ]
    }
  },
  {
    "inter": {
      "time": "2016-12-31T07:14:21.701194296533Z",
      "lat": -32.4653249,
      "fixFrac": 5717.701194296534,
      "lng": 148.98501687,
      "alt": 486.7
    },
    "cross": {
      "inZone": [
        false,
        true
      ],
      "crossingPair": [
        {
          "time": "2016-12-31T07:14:21Z",
          "lat": -32.46538333,
          "fix": 5717,
          "lng": 148.9849,
          "alt": 486
        },
        {
          "time": "2016-12-31T07:14:22Z",
          "lat": -32.4653,
          "fix": 5718,
          "lng": 148.98506667,
          "alt": 487
        }
      ]
    }
  }
]
